encodji/__init__.py
encodji-0.1.dist-info/DESCRIPTION.rst
encodji-0.1.dist-info/METADATA
encodji-0.1.dist-info/RECORD
encodji-0.1.dist-info/WHEEL
encodji-0.1.dist-info/metadata.json
encodji-0.1.dist-info/top_level.txt
