Metadata-Version: 2.0
Name: encodji
Version: 0.1
Summary: Encode data as emojis
Home-page: https://jacob.culley.me/encodji
Author: Jacob Culley
Author-email: jacob@culley.me
License: GPL3
Keywords: encodji emoji emojis encode
Platform: UNKNOWN
Requires-Python: >=3
